pyaotatrace/__init__.py
pyaotatrace/cfunc.py
pyaotatrace/types.py
pyaotatrace/wrapper.py
PyAotaTrace-0.0.5.dist-info/METADATA
PyAotaTrace-0.0.5.dist-info/WHEEL
PyAotaTrace-0.0.5.dist-info/top_level.txt
PyAotaTrace-0.0.5.dist-info/RECORD
