Metadata-Version: 2.1
Name: PyAotaTrace
Version: 0.0.5
Summary: 使用Python读取AOTA的Trace
Home-page: https://www.baidu.com
Author: Lizhenghao
Author-email: zhenghao2021@iscas.ac.cn
Maintainer: Lizhenghao
Maintainer-email: zhenghao2021@iscas.ac.cn
License: MIT
Platform: Linux
Classifier: Intended Audience :: Developers
Classifier: License :: OSI Approved :: MIT License
Classifier: Programming Language :: Python
Classifier: Programming Language :: Python :: 3.6
Classifier: Programming Language :: Python :: 3.7
Classifier: Programming Language :: Python :: 3.8
Classifier: Programming Language :: Python :: 3.9
